webshake/__init__.py
webshake/_version.py
webshake/parser.py
webshake/test_parser_fail.py
webshake/test_parser_success.py
webshake-0.0.1.dist-info/LICENSE
webshake-0.0.1.dist-info/METADATA
webshake-0.0.1.dist-info/WHEEL
webshake-0.0.1.dist-info/entry_points.txt
webshake-0.0.1.dist-info/top_level.txt
webshake-0.0.1.dist-info/RECORD
