Metadata-Version: 2.1
Name: webshake
Version: 0.0.1
Summary: WebEngine
Home-page: https://github.com/WebShake/webshake
Author: João Pinto
Author-email: lamego.pinto@gmail.com
License: BSD-3
Platform: UNKNOWN
